[{"Acc No": 241058495, "Transaction": "C", "Time Stamp": "2024-10-24 09:55:41.130145", "Amount": 34909}, {"Acc No": 241058160, "Transaction": "C", "Time Stamp": "2024-10-24 09:55:41.130172", "Amount": 90074}, {"Acc No": 241058644, "Transaction": "D", "Time Stamp": "2024-10-24 09:55:41.130182", "Amount": 51971}, {"Acc No": 241058843, "Transaction": "C", "Time Stamp": "2024-10-24 09:55:41.130190", "Amount": 18910}, {"Acc No": 241058890, "Transaction": "D", "Time Stamp": "2024-10-24 09:55:41.130198", "Amount": 85941}, {"Acc No": 241058065, "Transaction": "C", "Time Stamp": "2024-10-24 09:55:41.130206", "Amount": 88859}, {"Acc No": 241058555, "Transaction": "C", "Time Stamp": "2024-10-24 09:55:41.130215", "Amount": 23310}, {"Acc No": 241058117, "Transaction": "C", "Time Stamp": "2024-10-24 09:55:41.130225", "Amount": 91911}, {"Acc No": 241058335, "Transaction": "C", "Time Stamp": "2024-10-24 09:55:41.130235", "Amount": 68009}, {"Acc No": 241058538, "Transaction": "D", "Time Stamp": "2024-10-24 09:55:41.130243", "Amount": 94598}, {"Acc No": 241058923, "Transaction": "C", "Time Stamp": "2024-10-24 09:55:41.130251", "Amount": 26000}, {"Acc No": 241058059, "Transaction": "D", "Time Stamp": "2024-10-24 09:55:41.130260", "Amount": 16957}, {"Acc No": 241058357, "Transaction": "C", "Time Stamp": "2024-10-24 09:55:41.130269", "Amount": 73845}, {"Acc No": 241058636, "Transaction": "C", "Time Stamp": "2024-10-24 09:55:41.130276", "Amount": 17170}, {"Acc No": 241058741, "Transaction": "D", "Time Stamp": "2024-10-24 09:55:41.130284", "Amount": 36147}, {"Acc No": 241058471, "Transaction": "D", "Time Stamp": "2024-10-24 09:55:41.130293", "Amount": 83005}, {"Acc No": 241058310, "Transaction": "D", "Time Stamp": "2024-10-24 09:55:41.130301", "Amount": 15764}, {"Acc No": 241058857, "Transaction": "C", "Time Stamp": "2024-10-24 09:55:41.130309", "Amount": 57779}, {"Acc No": 241058219, "Transaction": "C", "Time Stamp": "2024-10-24 09:55:41.130318", "Amount": 87958}, {"Acc No": 241058759, "Transaction": "C", "Time Stamp": "2024-10-24 09:55:41.130327", "Amount": 61474}, {"Acc No": 241058572, "Transaction": "C", "Time Stamp": "2024-10-24 09:55:42.132302", "Amount": 92572}, {"Acc No": 241058471, "Transaction": "C", "Time Stamp": "2024-10-24 09:55:42.132335", "Amount": 53354}, {"Acc No": 241058228, "Transaction": "D", "Time Stamp": "2024-10-24 09:55:42.132343", "Amount": 98449}, {"Acc No": 241058945, "Transaction": "C", "Time Stamp": "2024-10-24 09:55:42.132349", "Amount": 15678}, {"Acc No": 241058670, "Transaction": "D", "Time Stamp": "2024-10-24 09:55:42.132355", "Amount": 34702}, {"Acc No": 241058050, "Transaction": "C", "Time Stamp": "2024-10-24 09:55:42.132364", "Amount": 35720}, {"Acc No": 241058179, "Transaction": "C", "Time Stamp": "2024-10-24 09:55:42.132370", "Amount": 12834}, {"Acc No": 241058214, "Transaction": "D", "Time Stamp": "2024-10-24 09:55:42.132375", "Amount": 82781}, {"Acc No": 241058160, "Transaction": "C", "Time Stamp": "2024-10-24 09:55:42.132382", "Amount": 72945}, {"Acc No": 241058172, "Transaction": "D", "Time Stamp": "2024-10-24 09:55:42.132387", "Amount": 27200}, {"Acc No": 241058406, "Transaction": "D", "Time Stamp": "2024-10-24 09:55:42.132393", "Amount": 54427}, {"Acc No": 241058813, "Transaction": "D", "Time Stamp": "2024-10-24 09:55:42.132399", "Amount": 17822}, {"Acc No": 241058854, "Transaction": "C", "Time Stamp": "2024-10-24 09:55:42.132406", "Amount": 78115}, {"Acc No": 241058286, "Transaction": "C", "Time Stamp": "2024-10-24 09:55:42.132412", "Amount": 27517}, {"Acc No": 241058246, "Transaction": "D", "Time Stamp": "2024-10-24 09:55:42.132417", "Amount": 52645}, {"Acc No": 241058390, "Transaction": "C", "Time Stamp": "2024-10-24 09:55:42.132423", "Amount": 66535}, {"Acc No": 241058059, "Transaction": "D", "Time Stamp": "2024-10-24 09:55:42.132428", "Amount": 12578}, {"Acc No": 241058741, "Transaction": "C", "Time Stamp": "2024-10-24 09:55:42.132434", "Amount": 21636}, {"Acc No": 241058004, "Transaction": "C", "Time Stamp": "2024-10-24 09:55:42.132439", "Amount": 63361}, {"Acc No": 241058181, "Transaction": "C", "Time Stamp": "2024-10-24 09:55:42.132444", "Amount": 1066}, {"Acc No": 241058738, "Transaction": "C", "Time Stamp": "2024-10-24 09:55:43.133602", "Amount": 65924}, {"Acc No": 241058949, "Transaction": "D", "Time Stamp": "2024-10-24 09:55:43.133640", "Amount": 70814}, {"Acc No": 241058424, "Transaction": "C", "Time Stamp": "2024-10-24 09:55:43.133647", "Amount": 62489}, {"Acc No": 241058524, "Transaction": "C", "Time Stamp": "2024-10-24 09:55:43.133653", "Amount": 88218}, {"Acc No": 241058806, "Transaction": "C", "Time Stamp": "2024-10-24 09:55:43.133660", "Amount": 94567}, {"Acc No": 241058533, "Transaction": "C", "Time Stamp": "2024-10-24 09:55:43.133665", "Amount": 56615}, {"Acc No": 241058720, "Transaction": "C", "Time Stamp": "2024-10-24 09:55:43.133671", "Amount": 85061}, {"Acc No": 241058474, "Transaction": "D", "Time Stamp": "2024-10-24 09:55:43.133677", "Amount": 72114}, {"Acc No": 241058024, "Transaction": "C", "Time Stamp": "2024-10-24 09:55:43.133683", "Amount": 78595}, {"Acc No": 241058123, "Transaction": "C", "Time Stamp": "2024-10-24 09:55:43.133689", "Amount": 19428}, {"Acc No": 241058256, "Transaction": "C", "Time Stamp": "2024-10-24 09:55:43.133694", "Amount": 33007}, {"Acc No": 241058331, "Transaction": "D", "Time Stamp": "2024-10-24 09:55:43.133700", "Amount": 8947}, {"Acc No": 241058113, "Transaction": "C", "Time Stamp": "2024-10-24 09:55:43.133705", "Amount": 44658}, {"Acc No": 241058047, "Transaction": "D", "Time Stamp": "2024-10-24 09:55:43.133711", "Amount": 21515}, {"Acc No": 241058459, "Transaction": "C", "Time Stamp": "2024-10-24 09:55:43.133717", "Amount": 36842}, {"Acc No": 241058489, "Transaction": "D", "Time Stamp": "2024-10-24 09:55:43.133723", "Amount": 62366}, {"Acc No": 241058455, "Transaction": "C", "Time Stamp": "2024-10-24 09:55:43.133728", "Amount": 15963}, {"Acc No": 241058289, "Transaction": "D", "Time Stamp": "2024-10-24 09:55:43.133733", "Amount": 26684}, {"Acc No": 241058027, "Transaction": "D", "Time Stamp": "2024-10-24 09:55:43.133739", "Amount": 31839}, {"Acc No": 241058567, "Transaction": "C", "Time Stamp": "2024-10-24 09:55:43.133745", "Amount": 73778}, {"Acc No": 241058438, "Transaction": "C", "Time Stamp": "2024-10-24 09:55:44.134136", "Amount": 41596}, {"Acc No": 241058232, "Transaction": "C", "Time Stamp": "2024-10-24 09:55:44.134195", "Amount": 32775}, {"Acc No": 241058451, "Transaction": "D", "Time Stamp": "2024-10-24 09:55:44.134205", "Amount": 82444}, {"Acc No": 241058881, "Transaction": "C", "Time Stamp": "2024-10-24 09:55:44.134214", "Amount": 42629}, {"Acc No": 241058278, "Transaction": "C", "Time Stamp": "2024-10-24 09:55:44.134222", "Amount": 2427}, {"Acc No": 241058256, "Transaction": "C", "Time Stamp": "2024-10-24 09:55:44.134232", "Amount": 84569}, {"Acc No": 241058430, "Transaction": "C", "Time Stamp": "2024-10-24 09:55:44.134241", "Amount": 92604}, {"Acc No": 241058467, "Transaction": "C", "Time Stamp": "2024-10-24 09:55:44.134250", "Amount": 22003}, {"Acc No": 241058329, "Transaction": "C", "Time Stamp": "2024-10-24 09:55:44.134258", "Amount": 40308}, {"Acc No": 241058645, "Transaction": "C", "Time Stamp": "2024-10-24 09:55:44.134266", "Amount": 39662}, {"Acc No": 241058140, "Transaction": "C", "Time Stamp": "2024-10-24 09:55:44.134275", "Amount": 14444}, {"Acc No": 241058626, "Transaction": "C", "Time Stamp": "2024-10-24 09:55:44.134284", "Amount": 72365}, {"Acc No": 241058974, "Transaction": "D", "Time Stamp": "2024-10-24 09:55:44.134293", "Amount": 92342}, {"Acc No": 241058768, "Transaction": "D", "Time Stamp": "2024-10-24 09:55:44.134301", "Amount": 29923}, {"Acc No": 241058961, "Transaction": "D", "Time Stamp": "2024-10-24 09:55:44.134310", "Amount": 53294}, {"Acc No": 241058678, "Transaction": "D", "Time Stamp": "2024-10-24 09:55:44.134319", "Amount": 15226}, {"Acc No": 241058538, "Transaction": "D", "Time Stamp": "2024-10-24 09:55:44.134326", "Amount": 47329}, {"Acc No": 241058924, "Transaction": "C", "Time Stamp": "2024-10-24 09:55:44.134339", "Amount": 63156}, {"Acc No": 241058425, "Transaction": "C", "Time Stamp": "2024-10-24 09:55:44.134347", "Amount": 25074}, {"Acc No": 241058698, "Transaction": "D", "Time Stamp": "2024-10-24 09:55:44.134356", "Amount": 18493}, {"Acc No": 241058474, "Transaction": "C", "Time Stamp": "2024-10-24 09:55:45.135195", "Amount": 53515}, {"Acc No": 241058667, "Transaction": "C", "Time Stamp": "2024-10-24 09:55:45.135239", "Amount": 54970}, {"Acc No": 241058681, "Transaction": "D", "Time Stamp": "2024-10-24 09:55:45.135250", "Amount": 18448}, {"Acc No": 241058103, "Transaction": "C", "Time Stamp": "2024-10-24 09:55:45.135259", "Amount": 58335}, {"Acc No": 241058607, "Transaction": "C", "Time Stamp": "2024-10-24 09:55:45.135269", "Amount": 73143}, {"Acc No": 241058007, "Transaction": "D", "Time Stamp": "2024-10-24 09:55:45.135279", "Amount": 20275}, {"Acc No": 241058450, "Transaction": "C", "Time Stamp": "2024-10-24 09:55:45.135288", "Amount": 87576}, {"Acc No": 241058930, "Transaction": "C", "Time Stamp": "2024-10-24 09:55:45.135297", "Amount": 13474}, {"Acc No": 241058831, "Transaction": "C", "Time Stamp": "2024-10-24 09:55:45.135307", "Amount": 28119}, {"Acc No": 241058258, "Transaction": "D", "Time Stamp": "2024-10-24 09:55:45.135316", "Amount": 7971}, {"Acc No": 241058637, "Transaction": "C", "Time Stamp": "2024-10-24 09:55:45.135325", "Amount": 14564}, {"Acc No": 241058589, "Transaction": "D", "Time Stamp": "2024-10-24 09:55:45.135335", "Amount": 97867}, {"Acc No": 241058726, "Transaction": "D", "Time Stamp": "2024-10-24 09:55:45.135345", "Amount": 3637}, {"Acc No": 241058399, "Transaction": "C", "Time Stamp": "2024-10-24 09:55:45.135355", "Amount": 36960}, {"Acc No": 241058024, "Transaction": "D", "Time Stamp": "2024-10-24 09:55:45.135365", "Amount": 63394}, {"Acc No": 241058237, "Transaction": "C", "Time Stamp": "2024-10-24 09:55:45.135374", "Amount": 55438}, {"Acc No": 241058904, "Transaction": "D", "Time Stamp": "2024-10-24 09:55:45.135383", "Amount": 8188}, {"Acc No": 241058029, "Transaction": "C", "Time Stamp": "2024-10-24 09:55:45.135393", "Amount": 52676}, {"Acc No": 241058013, "Transaction": "C", "Time Stamp": "2024-10-24 09:55:45.135402", "Amount": 63406}, {"Acc No": 241058258, "Transaction": "D", "Time Stamp": "2024-10-24 09:55:45.135411", "Amount": 45321}, {"Acc No": 241058108, "Transaction": "D", "Time Stamp": "2024-10-24 09:55:46.136173", "Amount": 70519}, {"Acc No": 241058176, "Transaction": "C", "Time Stamp": "2024-10-24 09:55:46.136218", "Amount": 81434}, {"Acc No": 241058802, "Transaction": "D", "Time Stamp": "2024-10-24 09:55:46.136229", "Amount": 30072}, {"Acc No": 241058816, "Transaction": "C", "Time Stamp": "2024-10-24 09:55:46.136240", "Amount": 8126}, {"Acc No": 241058616, "Transaction": "C", "Time Stamp": "2024-10-24 09:55:46.136250", "Amount": 56946}, {"Acc No": 241058755, "Transaction": "D", "Time Stamp": "2024-10-24 09:55:46.136260", "Amount": 35024}, {"Acc No": 241058627, "Transaction": "D", "Time Stamp": "2024-10-24 09:55:46.136270", "Amount": 51997}, {"Acc No": 241058736, "Transaction": "C", "Time Stamp": "2024-10-24 09:55:46.136280", "Amount": 96465}, {"Acc No": 241058935, "Transaction": "D", "Time Stamp": "2024-10-24 09:55:46.136289", "Amount": 4594}, {"Acc No": 241058129, "Transaction": "C", "Time Stamp": "2024-10-24 09:55:46.136302", "Amount": 52588}, {"Acc No": 241058799, "Transaction": "C", "Time Stamp": "2024-10-24 09:55:46.136311", "Amount": 52949}, {"Acc No": 241058154, "Transaction": "D", "Time Stamp": "2024-10-24 09:55:46.136321", "Amount": 65607}, {"Acc No": 241058492, "Transaction": "C", "Time Stamp": "2024-10-24 09:55:46.136332", "Amount": 46061}, {"Acc No": 241058717, "Transaction": "D", "Time Stamp": "2024-10-24 09:55:46.136341", "Amount": 51797}, {"Acc No": 241058056, "Transaction": "C", "Time Stamp": "2024-10-24 09:55:46.136351", "Amount": 58017}, {"Acc No": 241058550, "Transaction": "D", "Time Stamp": "2024-10-24 09:55:46.136360", "Amount": 73880}, {"Acc No": 241058913, "Transaction": "C", "Time Stamp": "2024-10-24 09:55:46.136369", "Amount": 16234}, {"Acc No": 241058696, "Transaction": "C", "Time Stamp": "2024-10-24 09:55:46.136379", "Amount": 58676}, {"Acc No": 241058315, "Transaction": "D", "Time Stamp": "2024-10-24 09:55:46.136388", "Amount": 46094}, {"Acc No": 241058491, "Transaction": "D", "Time Stamp": "2024-10-24 09:55:46.136397", "Amount": 54628}, {"Acc No": 241058347, "Transaction": "D", "Time Stamp": "2024-10-24 09:55:47.137186", "Amount": 50474}, {"Acc No": 241058176, "Transaction": "D", "Time Stamp": "2024-10-24 09:55:47.137231", "Amount": 22374}, {"Acc No": 241058618, "Transaction": "C", "Time Stamp": "2024-10-24 09:55:47.137242", "Amount": 15698}, {"Acc No": 241058023, "Transaction": "D", "Time Stamp": "2024-10-24 09:55:47.137251", "Amount": 7415}, {"Acc No": 241058053, "Transaction": "D", "Time Stamp": "2024-10-24 09:55:47.137261", "Amount": 23981}, {"Acc No": 241058410, "Transaction": "D", "Time Stamp": "2024-10-24 09:55:47.137270", "Amount": 24778}, {"Acc No": 241058848, "Transaction": "D", "Time Stamp": "2024-10-24 09:55:47.137279", "Amount": 79668}, {"Acc No": 241058847, "Transaction": "C", "Time Stamp": "2024-10-24 09:55:47.137288", "Amount": 29350}, {"Acc No": 241058456, "Transaction": "D", "Time Stamp": "2024-10-24 09:55:47.137298", "Amount": 36468}, {"Acc No": 241058023, "Transaction": "D", "Time Stamp": "2024-10-24 09:55:47.137310", "Amount": 50150}, {"Acc No": 241058880, "Transaction": "D", "Time Stamp": "2024-10-24 09:55:47.137319", "Amount": 89273}, {"Acc No": 241058001, "Transaction": "D", "Time Stamp": "2024-10-24 09:55:47.137328", "Amount": 38720}, {"Acc No": 241058364, "Transaction": "C", "Time Stamp": "2024-10-24 09:55:47.137337", "Amount": 25320}, {"Acc No": 241058136, "Transaction": "C", "Time Stamp": "2024-10-24 09:55:47.137348", "Amount": 31528}, {"Acc No": 241058974, "Transaction": "C", "Time Stamp": "2024-10-24 09:55:47.137357", "Amount": 77292}, {"Acc No": 241058964, "Transaction": "C", "Time Stamp": "2024-10-24 09:55:47.137365", "Amount": 71133}, {"Acc No": 241058866, "Transaction": "D", "Time Stamp": "2024-10-24 09:55:47.137374", "Amount": 47320}, {"Acc No": 241058066, "Transaction": "D", "Time Stamp": "2024-10-24 09:55:47.137383", "Amount": 36064}, {"Acc No": 241058596, "Transaction": "C", "Time Stamp": "2024-10-24 09:55:47.137391", "Amount": 60543}, {"Acc No": 241058132, "Transaction": "D", "Time Stamp": "2024-10-24 09:55:47.137400", "Amount": 59015}, {"Acc No": 241058982, "Transaction": "D", "Time Stamp": "2024-10-24 09:55:48.138544", "Amount": 97494}, {"Acc No": 241058331, "Transaction": "D", "Time Stamp": "2024-10-24 09:55:48.138578", "Amount": 10274}, {"Acc No": 241058993, "Transaction": "D", "Time Stamp": "2024-10-24 09:55:48.138586", "Amount": 11538}, {"Acc No": 241058176, "Transaction": "D", "Time Stamp": "2024-10-24 09:55:48.138592", "Amount": 66884}, {"Acc No": 241058334, "Transaction": "C", "Time Stamp": "2024-10-24 09:55:48.138599", "Amount": 22649}, {"Acc No": 241058267, "Transaction": "D", "Time Stamp": "2024-10-24 09:55:48.138605", "Amount": 42682}, {"Acc No": 241058696, "Transaction": "C", "Time Stamp": "2024-10-24 09:55:48.138610", "Amount": 41577}, {"Acc No": 241058748, "Transaction": "C", "Time Stamp": "2024-10-24 09:55:48.138616", "Amount": 88535}, {"Acc No": 241058685, "Transaction": "D", "Time Stamp": "2024-10-24 09:55:48.138622", "Amount": 49208}, {"Acc No": 241058982, "Transaction": "C", "Time Stamp": "2024-10-24 09:55:48.138629", "Amount": 3253}, {"Acc No": 241058842, "Transaction": "D", "Time Stamp": "2024-10-24 09:55:48.138635", "Amount": 98280}, {"Acc No": 241058038, "Transaction": "C", "Time Stamp": "2024-10-24 09:55:48.138641", "Amount": 76272}, {"Acc No": 241058430, "Transaction": "D", "Time Stamp": "2024-10-24 09:55:48.138647", "Amount": 91938}, {"Acc No": 241058699, "Transaction": "C", "Time Stamp": "2024-10-24 09:55:48.138655", "Amount": 36107}, {"Acc No": 241058593, "Transaction": "D", "Time Stamp": "2024-10-24 09:55:48.138662", "Amount": 81839}, {"Acc No": 241058170, "Transaction": "D", "Time Stamp": "2024-10-24 09:55:48.138667", "Amount": 39212}, {"Acc No": 241058072, "Transaction": "C", "Time Stamp": "2024-10-24 09:55:48.138673", "Amount": 55777}, {"Acc No": 241058782, "Transaction": "C", "Time Stamp": "2024-10-24 09:55:48.138679", "Amount": 91700}, {"Acc No": 241058836, "Transaction": "C", "Time Stamp": "2024-10-24 09:55:48.138684", "Amount": 36039}, {"Acc No": 241058211, "Transaction": "C", "Time Stamp": "2024-10-24 09:55:48.138690", "Amount": 97895}, {"Acc No": 241058011, "Transaction": "C", "Time Stamp": "2024-10-24 09:55:49.139815", "Amount": 51918}, {"Acc No": 241058338, "Transaction": "C", "Time Stamp": "2024-10-24 09:55:49.139855", "Amount": 45532}, {"Acc No": 241058916, "Transaction": "D", "Time Stamp": "2024-10-24 09:55:49.139862", "Amount": 93400}, {"Acc No": 241058255, "Transaction": "D", "Time Stamp": "2024-10-24 09:55:49.139868", "Amount": 75968}, {"Acc No": 241058099, "Transaction": "C", "Time Stamp": "2024-10-24 09:55:49.139874", "Amount": 4745}, {"Acc No": 241058616, "Transaction": "D", "Time Stamp": "2024-10-24 09:55:49.139880", "Amount": 69665}, {"Acc No": 241058019, "Transaction": "C", "Time Stamp": "2024-10-24 09:55:49.139886", "Amount": 66175}, {"Acc No": 241058140, "Transaction": "D", "Time Stamp": "2024-10-24 09:55:49.139892", "Amount": 18675}, {"Acc No": 241058631, "Transaction": "C", "Time Stamp": "2024-10-24 09:55:49.139899", "Amount": 34983}, {"Acc No": 241058260, "Transaction": "D", "Time Stamp": "2024-10-24 09:55:49.139905", "Amount": 82721}, {"Acc No": 241058469, "Transaction": "C", "Time Stamp": "2024-10-24 09:55:49.139911", "Amount": 30494}, {"Acc No": 241058432, "Transaction": "D", "Time Stamp": "2024-10-24 09:55:49.139917", "Amount": 89467}, {"Acc No": 241058575, "Transaction": "C", "Time Stamp": "2024-10-24 09:55:49.139923", "Amount": 9106}, {"Acc No": 241058412, "Transaction": "C", "Time Stamp": "2024-10-24 09:55:49.139933", "Amount": 97926}, {"Acc No": 241058914, "Transaction": "C", "Time Stamp": "2024-10-24 09:55:49.139939", "Amount": 84981}, {"Acc No": 241058518, "Transaction": "C", "Time Stamp": "2024-10-24 09:55:49.139945", "Amount": 93273}, {"Acc No": 241058642, "Transaction": "C", "Time Stamp": "2024-10-24 09:55:49.139950", "Amount": 1649}, {"Acc No": 241058106, "Transaction": "D", "Time Stamp": "2024-10-24 09:55:49.139956", "Amount": 65309}, {"Acc No": 241058446, "Transaction": "D", "Time Stamp": "2024-10-24 09:55:49.139961", "Amount": 72592}, {"Acc No": 241058028, "Transaction": "C", "Time Stamp": "2024-10-24 09:55:49.139967", "Amount": 97952}, {"Acc No": 241058270, "Transaction": "C", "Time Stamp": "2024-10-24 09:55:50.141153", "Amount": 3985}, {"Acc No": 241058709, "Transaction": "C", "Time Stamp": "2024-10-24 09:55:50.141194", "Amount": 9039}, {"Acc No": 241058093, "Transaction": "D", "Time Stamp": "2024-10-24 09:55:50.141201", "Amount": 50329}, {"Acc No": 241058640, "Transaction": "D", "Time Stamp": "2024-10-24 09:55:50.141207", "Amount": 67035}, {"Acc No": 241058732, "Transaction": "C", "Time Stamp": "2024-10-24 09:55:50.141213", "Amount": 59350}, {"Acc No": 241058546, "Transaction": "C", "Time Stamp": "2024-10-24 09:55:50.141218", "Amount": 37601}, {"Acc No": 241058107, "Transaction": "D", "Time Stamp": "2024-10-24 09:55:50.141224", "Amount": 44149}, {"Acc No": 241058244, "Transaction": "C", "Time Stamp": "2024-10-24 09:55:50.141230", "Amount": 45708}, {"Acc No": 241058217, "Transaction": "D", "Time Stamp": "2024-10-24 09:55:50.141236", "Amount": 20841}, {"Acc No": 241058907, "Transaction": "C", "Time Stamp": "2024-10-24 09:55:50.141242", "Amount": 86954}, {"Acc No": 241058324, "Transaction": "C", "Time Stamp": "2024-10-24 09:55:50.141247", "Amount": 16897}, {"Acc No": 241058026, "Transaction": "D", "Time Stamp": "2024-10-24 09:55:50.141253", "Amount": 48209}, {"Acc No": 241058235, "Transaction": "C", "Time Stamp": "2024-10-24 09:55:50.141259", "Amount": 29463}, {"Acc No": 241058034, "Transaction": "C", "Time Stamp": "2024-10-24 09:55:50.141265", "Amount": 73960}, {"Acc No": 241058126, "Transaction": "D", "Time Stamp": "2024-10-24 09:55:50.141271", "Amount": 29982}, {"Acc No": 241058968, "Transaction": "C", "Time Stamp": "2024-10-24 09:55:50.141277", "Amount": 19578}, {"Acc No": 241058435, "Transaction": "D", "Time Stamp": "2024-10-24 09:55:50.141282", "Amount": 57582}, {"Acc No": 241058513, "Transaction": "D", "Time Stamp": "2024-10-24 09:55:50.141288", "Amount": 8498}, {"Acc No": 241058772, "Transaction": "C", "Time Stamp": "2024-10-24 09:55:50.141293", "Amount": 52391}, {"Acc No": 241058396, "Transaction": "C", "Time Stamp": "2024-10-24 09:55:50.141299", "Amount": 30797}]